fftoptionlib/__init__.py
fftoptionlib/characteristic_funs.py
fftoptionlib/cosine_pricer.py
fftoptionlib/engine_class.py
fftoptionlib/fourier_pricer.py
fftoptionlib/helper.py
fftoptionlib/moment_generating_funs.py
fftoptionlib/option_class.py
fftoptionlib/pricing_class.py
fftoptionlib/process_class.py
fftoptionlib/version.py
fftoptionlib-0.1.2.dist-info/METADATA
fftoptionlib-0.1.2.dist-info/RECORD
fftoptionlib-0.1.2.dist-info/WHEEL
fftoptionlib-0.1.2.dist-info/top_level.txt
