Metadata-Version: 2.1
Name: fftoptionlib
Version: 0.1.2
Summary: FFT-based Option Pricing Method in Python
Home-page: https://github.com/arraystream/fftoptionlib
Author: ArrayStream (Yu Zheng, Ran Fan)
Author-email: team@arraystream.com
License: BSD
Platform: any
Classifier: Development Status :: 5 - Production/Stable
Classifier: Programming Language :: Python :: 3
Classifier: Programming Language :: Python :: 3.3
Classifier: Programming Language :: Python :: 3.4
Classifier: Programming Language :: Python :: 3.5
Classifier: Topic :: Scientific/Engineering :: Mathematics
Classifier: Intended Audience :: Financial and Insurance Industry
Requires-Dist: numpy
Requires-Dist: scipy
Requires-Dist: pandas
Requires-Dist: autograd
